fbl/__init__.py
fbl/__main__.py
fbl-0.9.2.dist-info/LICENSE
fbl-0.9.2.dist-info/METADATA
fbl-0.9.2.dist-info/WHEEL
fbl-0.9.2.dist-info/entry_points.txt
fbl-0.9.2.dist-info/top_level.txt
fbl-0.9.2.dist-info/RECORD
