Metadata-Version: 2.1
Name: fbl
Version: 0.9.2
Summary: FBL is tool to find broken links in articles and files
Home-page: https://github.com/mr-tafreshi/fbl
Author: Amirmahdi Tafreshi
Author-email: a.tafreshi440@gmail.com
License: UNKNOWN
Platform: UNKNOWN
Classifier: Programming Language :: Python :: 3
Classifier: License :: OSI Approved :: MIT License
Classifier: Operating System :: OS Independent
Requires-Python: >=3.6
Requires-Dist: certifi (==2020.12.5)
Requires-Dist: chardet (==4.0.0)
Requires-Dist: idna (==2.10)
Requires-Dist: lxml (==4.6.3)
Requires-Dist: PyMuPDF (==1.18.6)
Requires-Dist: python-docx (==0.8.10)
Requires-Dist: requests (==2.25.1)
Requires-Dist: urllib3 (==1.26.5)
Requires-Dist: ODTtoText (==0.0.1)
